odoo8_addon_stock_picking_compute_delivery_date-8.0.1.1.0.99.dev26-py3.8-nspkg.pth
odoo_addons/stock_picking_compute_delivery_date/README.rst
odoo_addons/stock_picking_compute_delivery_date/__init__.py
odoo_addons/stock_picking_compute_delivery_date/__openerp__.py
odoo_addons/stock_picking_compute_delivery_date/data/cron.xml
odoo_addons/stock_picking_compute_delivery_date/i18n/am.po
odoo_addons/stock_picking_compute_delivery_date/i18n/ar.po
odoo_addons/stock_picking_compute_delivery_date/i18n/bg.po
odoo_addons/stock_picking_compute_delivery_date/i18n/bs.po
odoo_addons/stock_picking_compute_delivery_date/i18n/ca.po
odoo_addons/stock_picking_compute_delivery_date/i18n/ca_ES.po
odoo_addons/stock_picking_compute_delivery_date/i18n/cs.po
odoo_addons/stock_picking_compute_delivery_date/i18n/da.po
odoo_addons/stock_picking_compute_delivery_date/i18n/de.po
odoo_addons/stock_picking_compute_delivery_date/i18n/el_GR.po
odoo_addons/stock_picking_compute_delivery_date/i18n/en_AU.po
odoo_addons/stock_picking_compute_delivery_date/i18n/en_GB.po
odoo_addons/stock_picking_compute_delivery_date/i18n/es.po
odoo_addons/stock_picking_compute_delivery_date/i18n/es_AR.po
odoo_addons/stock_picking_compute_delivery_date/i18n/es_CL.po
odoo_addons/stock_picking_compute_delivery_date/i18n/es_CO.po
odoo_addons/stock_picking_compute_delivery_date/i18n/es_CR.po
odoo_addons/stock_picking_compute_delivery_date/i18n/es_DO.po
odoo_addons/stock_picking_compute_delivery_date/i18n/es_EC.po
odoo_addons/stock_picking_compute_delivery_date/i18n/es_ES.po
odoo_addons/stock_picking_compute_delivery_date/i18n/es_MX.po
odoo_addons/stock_picking_compute_delivery_date/i18n/es_PE.po
odoo_addons/stock_picking_compute_delivery_date/i18n/es_PY.po
odoo_addons/stock_picking_compute_delivery_date/i18n/es_VE.po
odoo_addons/stock_picking_compute_delivery_date/i18n/et.po
odoo_addons/stock_picking_compute_delivery_date/i18n/eu.po
odoo_addons/stock_picking_compute_delivery_date/i18n/fa.po
odoo8_addon_stock_picking_compute_delivery_date-8.0.1.1.0.99.dev26.dist-info/METADATA
odoo8_addon_stock_picking_compute_delivery_date-8.0.1.1.0.99.dev26.dist-info/WHEEL
odoo8_addon_stock_picking_compute_delivery_date-8.0.1.1.0.99.dev26.dist-info/namespace_packages.txt
odoo8_addon_stock_picking_compute_delivery_date-8.0.1.1.0.99.dev26.dist-info/top_level.txt
odoo8_addon_stock_picking_compute_delivery_date-8.0.1.1.0.99.dev26.dist-info/RECORD
